{
  "_KMKxkoLKv": {
    "pageNum": 281,
    "number": 5607,
    "text": {
      "tags": [
        "哲理",
        "人生",
        "修身养性"
      ],
      "likes": 876,
      "bookmarks": 327
    }
  },
  "0y5LPLEm1j": {
    "pageNum": 281,
    "number": 5608,
    "text": {
      "tags": [
        "爱情",
        "思念",
        "离别"
      ],
      "likes": 2567,
      "bookmarks": 789
    }
  },
  "UhNn5eQXDc": {
    "pageNum": 281,
    "number": 5609,
    "text": {
      "tags": [
        "离别",
        "思乡",
        "季节"
      ],
      "likes": 127,
      "bookmarks": 37
    }
  },
  "t5oXO0EoEU": {
    "pageNum": 281,
    "number": 5610,
    "text": {
      "tags": [
        "道德",
        "正义",
        "报应"
      ],
      "likes": 127,
      "bookmarks": 42
    }
  },
  "xu4QB1N6UL": {
    "pageNum": 281,
    "number": 5611,
    "text": {
      "tags": [
        "怀旧",
        "思念",
        "古风"
      ],
      "likes": 1287,
      "bookmarks": 456
    }
  },
  "yKgB9Zj3lI": {
    "pageNum": 281,
    "number": 5612,
    "text": {
      "tags": [
        "婚礼",
        "喜庆",
        "美好"
      ],
      "likes": 128,
      "bookmarks": 37
    }
  },
  "dQOq0tkxtX": {
    "pageNum": 281,
    "number": 5613,
    "text": {
      "tags": [
        "文学",
        "诗歌",
        "赞美"
      ],
      "likes": 127,
      "bookmarks": 42
    }
  },
  "JJhmHD_chM": {
    "pageNum": 281,
    "number": 5614,
    "text": {
      "tags": [
        "忠诚",
        "执着",
        "尊重",
        "传统"
      ],
      "likes": 127,
      "bookmarks": 42
    }
  },
  "x361yWHlhs": {
    "pageNum": 281,
    "number": 5615,
    "text": {
      "tags": [
        "诗歌",
        "文学",
        "古风"
      ],
      "likes": 87,
      "bookmarks": 32
    }
  },
  "531CtMB-dj": {
    "pageNum": 281,
    "number": 5616,
    "text": {
      "tags": [
        "自然",
        "园林",
        "竹林",
        "山水"
      ],
      "likes": 127,
      "bookmarks": 42
    }
  },
  "H6dyAR2pw5": {
    "pageNum": 281,
    "number": 5617,
    "text": {
      "tags": [
        "雨",
        "心情",
        "古风"
      ],
      "likes": 127,
      "bookmarks": 42
    }
  },
  "SmxHFgiL_A": {
    "pageNum": 281,
    "number": 5618,
    "text": {
      "tags": [
        "乡愁",
        "故乡",
        "亲情"
      ],
      "likes": 127,
      "bookmarks": 37
    }
  },
  "I24xCWUe0S": {
    "pageNum": 281,
    "number": 5619,
    "text": {
      "tags": [
        "旅行",
        "自然景观",
        "冬季"
      ],
      "likes": 127,
      "bookmarks": 42
    }
  },
  "J7ZdrX8uqz": {
    "pageNum": 281,
    "number": 5620,
    "text": {
      "tags": [
        "爱情",
        "思念",
        "诗歌"
      ],
      "likes": 127,
      "bookmarks": 37
    }
  },
  "-sqWQftMhJ": {
    "pageNum": 282,
    "number": 5621,
    "text": {
      "tags": [
        "古诗词",
        "哲理"
      ],
      "likes": 137,
      "bookmarks": 42
    }
  },
  "BebzThudPP": {
    "pageNum": 282,
    "number": 5622,
    "text": {
      "tags": [
        "江河",
        "自然景观",
        "时光流转"
      ],
      "likes": 87,
      "bookmarks": 32
    }
  },
  "BWGm3PsPAY": {
    "pageNum": 282,
    "number": 5623,
    "text": {
      "tags": [
        "清晨",
        "天气",
        "自然"
      ],
      "likes": 87,
      "bookmarks": 32
    }
  },
  "Lj8d77iFxD": {
    "pageNum": 282,
    "number": 5625,
    "text": {
      "tags": [
        "诗歌",
        "月亮",
        "自然"
      ],
      "likes": 127,
      "bookmarks": 42
    }
  },
  "Jf9bro5imG": {
    "pageNum": 282,
    "number": 5626,
    "text": {
      "tags": [
        "时间",
        "流逝",
        "失落"
      ],
      "likes": 127,
      "bookmarks": 42
    }
  },
  "cTPMQ9Ztcw": {
    "pageNum": 282,
    "number": 5627,
    "text": {
      "tags": [
        "山水",
        "自然",
        "景色"
      ],
      "likes": 127,
      "bookmarks": 42
    }
  },
  "RnYBfrrTbq": {
    "pageNum": 282,
    "number": 5629,
    "text": {
      "tags": [
        "春天",
        "自然景观",
        "诗歌"
      ],
      "likes": 127,
      "bookmarks": 42
    }
  },
  "LonNiwTQRO": {
    "pageNum": 282,
    "number": 5630,
    "text": {
      "tags": [
        "自由",
        "飞行",
        "远离尘世"
      ],
      "likes": 127,
      "bookmarks": 37
    }
  },
  "SIoMb0q8x2": {
    "pageNum": 282,
    "number": 5631,
    "text": {
      "tags": [
        "官场",
        "权力",
        "政治"
      ],
      "likes": 127,
      "bookmarks": 42
    }
  },
  "gcasCSSAjw": {
    "pageNum": 282,
    "number": 5632,
    "text": {
      "tags": [
        "星空",
        "自然景观",
        "河流"
      ],
      "likes": 127,
      "bookmarks": 37
    }
  },
  "ixLbjCC5Fi": {
    "pageNum": 282,
    "number": 5633,
    "text": {
      "tags": [
        "自然",
        "意境",
        "水景"
      ],
      "likes": 127,
      "bookmarks": 42
    }
  },
  "MnSyMcN-8I": {
    "pageNum": 282,
    "number": 5634,
    "text": {
      "tags": [
        "离别",
        "思念",
        "诗歌"
      ],
      "likes": 256,
      "bookmarks": 87
    }
  },
  "H_FRc3Ncd0": {
    "pageNum": 282,
    "number": 5635,
    "text": {
      "tags": [
        "危机",
        "转机",
        "困境",
        "挑战"
      ],
      "likes": 127,
      "bookmarks": 42
    }
  },
  "oxje90QRQQ": {
    "pageNum": 282,
    "number": 5636,
    "text": {
      "tags": [
        "诗歌",
        "自然",
        "美食"
      ],
      "likes": 127,
      "bookmarks": 42
    }
  },
  "uIjgoTreB-": {
    "pageNum": 282,
    "number": 5638,
    "text": {
      "tags": [
        "爱",
        "报答",
        "感恩"
      ],
      "likes": 127,
      "bookmarks": 37
    }
  },
  "PUk2FYW9bG": {
    "pageNum": 282,
    "number": 5639,
    "text": {
      "tags": [
        "田园",
        "农村",
        "清晨",
        "劳动"
      ],
      "likes": 127,
      "bookmarks": 42
    }
  },
  "28RmMeMdnU": {
    "pageNum": 282,
    "number": 5640,
    "text": {
      "tags": [
        "离别",
        "思乡",
        "伤感"
      ],
      "likes": 2567,
      "bookmarks": 789
    }
  },
  "DlLLoISZuN": {
    "pageNum": 283,
    "number": 5641,
    "text": {
      "tags": [
        "古诗词",
        "女性"
      ],
      "likes": 127,
      "bookmarks": 42
    }
  },
  "QRhxW8-v8z": {
    "pageNum": 283,
    "number": 5642,
    "text": {
      "tags": [
        "旅行",
        "探险",
        "历史"
      ],
      "likes": 127,
      "bookmarks": 42
    }
  },
  "Xpg3_0Zd5G": {
    "pageNum": 283,
    "number": 5643,
    "text": {
      "tags": [
        "思乡",
        "忧伤",
        "回忆",
        "人生"
      ],
      "likes": 127,
      "bookmarks": 42
    }
  },
  "N0kVr7c89F": {
    "pageNum": 283,
    "number": 5644,
    "text": {
      "tags": [
        "历史",
        "功绩",
        "忠诚"
      ],
      "likes": 1287,
      "bookmarks": 567
    }
  },
  "s6D6tWD5Xs": {
    "pageNum": 283,
    "number": 5645,
    "text": {
      "tags": [
        "诗歌",
        "自然",
        "风景"
      ],
      "likes": 127,
      "bookmarks": 42
    }
  },
  "xmzdEUiRGs": {
    "pageNum": 283,
    "number": 5646,
    "text": {
      "tags": [
        "谚语",
        "社会",
        "传播"
      ],
      "likes": 127,
      "bookmarks": 42
    }
  },
  "wWLPy7KsEo": {
    "pageNum": 283,
    "number": 5647,
    "text": {
      "tags": [
        "美食",
        "饮食"
      ],
      "likes": 127,
      "bookmarks": 42
    }
  },
  "j4dFSa-LDJ": {
    "pageNum": 283,
    "number": 5648,
    "text": {
      "tags": [
        "古诗词",
        "礼仪",
        "传统文化"
      ],
      "likes": 87,
      "bookmarks": 32
    }
  },
  "ZC4WIFZ8Eu": {
    "pageNum": 283,
    "number": 5649,
    "text": {
      "tags": [
        "爱国",
        "忠诚"
      ],
      "likes": 1287,
      "bookmarks": 567
    }
  },
  "JFLW7fUvjO": {
    "pageNum": 283,
    "number": 5650,
    "text": {
      "tags": [
        "友情",
        "读书",
        "风流"
      ],
      "likes": 127,
      "bookmarks": 42
    }
  },
  "69tQoYHC8d": {
    "pageNum": 283,
    "number": 5651,
    "text": {
      "tags": [
        "诗歌",
        "禅意",
        "哲理"
      ],
      "likes": 127,
      "bookmarks": 42
    }
  },
  "S6Y8yq8uIP": {
    "pageNum": 283,
    "number": 5652,
    "text": {
      "tags": [
        "自然",
        "风景",
        "城市"
      ],
      "likes": 127,
      "bookmarks": 42
    }
  },
  "cVVuKXwRFZ": {
    "pageNum": 283,
    "number": 5653,
    "text": {
      "tags": [
        "离别",
        "思念",
        "远方"
      ],
      "likes": 127,
      "bookmarks": 42
    }
  },
  "7_eYa_YKKk": {
    "pageNum": 283,
    "number": 5654,
    "text": {
      "tags": [
        "旅游",
        "风景",
        "诗歌"
      ],
      "likes": 127,
      "bookmarks": 42
    }
  },
  "tGRZtzHrRZ": {
    "pageNum": 283,
    "number": 5655,
    "text": {
      "tags": [
        "家庭",
        "亲情",
        "爱情",
        "教育"
      ],
      "likes": 1287,
      "bookmarks": 567
    }
  },
  "Vz-rCQWKLs": {
    "pageNum": 283,
    "number": 5656,
    "text": {
      "tags": [
        "夜晚",
        "凉爽",
        "感受"
      ],
      "likes": 127,
      "bookmarks": 42
    }
  },
  "fF4wvqNpZz": {
    "pageNum": 283,
    "number": 5657,
    "text": {
      "tags": [
        "诗歌",
        "意境",
        "孤独"
      ],
      "likes": 127,
      "bookmarks": 37
    }
  },
  "axA-eMiLrO": {
    "pageNum": 283,
    "number": 5658,
    "text": {
      "tags": [
        "人生哲理",
        "追求财富",
        "自我价值"
      ],
      "likes": 876,
      "bookmarks": 427
    }
  },
  "P_VB-fuVUh": {
    "pageNum": 283,
    "number": 5659,
    "text": {
      "tags": [
        "哲理",
        "人生",
        "行动"
      ],
      "likes": 127,
      "bookmarks": 57
    }
  },
  "qCW8qiWakZ": {
    "pageNum": 283,
    "number": 5660,
    "text": {
      "tags": [
        "离愁",
        "怀旧",
        "回忆",
        "古风"
      ],
      "likes": 327,
      "bookmarks": 87
    }
  },
  "HnLdR7RxKp": {
    "pageNum": 284,
    "number": 5661,
    "text": {
      "tags": [
        "自然景观",
        "湖泊",
        "山脉",
        "动物"
      ],
      "likes": 127,
      "bookmarks": 42
    }
  },
  "Pg-Beh_O5r": {
    "pageNum": 284,
    "number": 5662,
    "text": {
      "tags": [
        "旅游",
        "文化",
        "历史"
      ],
      "likes": 127,
      "bookmarks": 42
    }
  },
  "NfHnLUWfOK": {
    "pageNum": 284,
    "number": 5663,
    "text": {
      "tags": [
        "自然",
        "诗意",
        "寂静"
      ],
      "likes": 127,
      "bookmarks": 37
    }
  },
  "xgwCjfSgby": {
    "pageNum": 284,
    "number": 5664,
    "text": {
      "tags": [
        "诗歌",
        "山水",
        "艺术"
      ],
      "likes": 127,
      "bookmarks": 42
    }
  },
  "QApQ5I6wed": {
    "pageNum": 284,
    "number": 5665,
    "text": {
      "tags": [
        "生活",
        "饮食",
        "健康",
        "季节"
      ],
      "likes": 127,
      "bookmarks": 42
    }
  },
  "8UD66HL_nO": {
    "pageNum": 284,
    "number": 5666,
    "text": {
      "tags": [
        "历史",
        "文化",
        "传统"
      ],
      "likes": 238,
      "bookmarks": 57
    }
  },
  "psuGap4ir1": {
    "pageNum": 284,
    "number": 5667,
    "text": {
      "tags": [
        "离别",
        "悲伤",
        "诗歌"
      ],
      "likes": 127,
      "bookmarks": 37
    }
  },
  "jlsalPtnO-": {
    "pageNum": 284,
    "number": 5668,
    "text": {
      "tags": [
        "诗歌",
        "自然",
        "清新"
      ],
      "likes": 127,
      "bookmarks": 42
    }
  },
  "apaKP1Idp3": {
    "pageNum": 284,
    "number": 5669,
    "text": {
      "tags": [
        "自然",
        "动物",
        "生态"
      ],
      "likes": 127,
      "bookmarks": 42
    }
  },
  "H2KD_VBsLP": {
    "pageNum": 284,
    "number": 5670,
    "text": {
      "tags": [
        "自然",
        "风景",
        "友谊"
      ],
      "likes": 127,
      "bookmarks": 42
    }
  },
  "9CY_hYgMDt": {
    "pageNum": 284,
    "number": 5671,
    "text": {
      "tags": [
        "历史",
        "文化",
        "传统"
      ],
      "likes": 128,
      "bookmarks": 37
    }
  },
  "ijIBWRthel": {
    "pageNum": 284,
    "number": 5672,
    "text": {
      "tags": [
        "清新",
        "优美",
        "音乐"
      ],
      "likes": 256,
      "bookmarks": 87
    }
  },
  "l5QYO0vMbv": {
    "pageNum": 284,
    "number": 5673,
    "text": {
      "tags": [
        "历史",
        "古代",
        "政治"
      ],
      "likes": 37,
      "bookmarks": 8
    }
  },
  "vtzG8T5-SD": {
    "pageNum": 284,
    "number": 5674,
    "text": {
      "tags": [
        "家庭",
        "亲情",
        "孙子"
      ],
      "likes": 127,
      "bookmarks": 42
    }
  },
  "77LtceBDPr": {
    "pageNum": 284,
    "number": 5675,
    "text": {
      "tags": [
        "迷惑",
        "困惑",
        "疑问"
      ],
      "likes": 37,
      "bookmarks": 8
    }
  },
  "azOyg979yA": {
    "pageNum": 284,
    "number": 5676,
    "text": {
      "tags": [
        "山水",
        "自然",
        "壮美"
      ],
      "likes": 876,
      "bookmarks": 327
    }
  },
  "G0ldeyXgBS": {
    "pageNum": 284,
    "number": 5677,
    "text": {
      "tags": [
        "军事",
        "权威",
        "威严"
      ],
      "likes": 127,
      "bookmarks": 37
    }
  },
  "Fjqz6uSABk": {
    "pageNum": 284,
    "number": 5678,
    "text": {
      "tags": [
        "古风",
        "怀旧",
        "伤感",
        "音乐"
      ],
      "likes": 256,
      "bookmarks": 87
    }
  },
  "0I3qc9CupR": {
    "pageNum": 284,
    "number": 5679,
    "text": {
      "tags": [
        "自然",
        "植物",
        "美景"
      ],
      "likes": 127,
      "bookmarks": 42
    }
  },
  "hJ_YfFgjlL": {
    "pageNum": 284,
    "number": 5680,
    "text": {
      "tags": [
        "历史",
        "传说",
        "帝王"
      ],
      "likes": 127,
      "bookmarks": 42
    }
  },
  "tCZ9G3PGwK": {
    "pageNum": 285,
    "number": 5681,
    "text": {
      "tags": [
        "离愁",
        "孤独",
        "落寞",
        "黄昏"
      ],
      "likes": 127,
      "bookmarks": 37
    }
  },
  "KlFxD3Z_u9": {
    "pageNum": 285,
    "number": 5682,
    "text": {
      "tags": [
        "自然",
        "生态",
        "环境"
      ],
      "likes": 87,
      "bookmarks": 32
    }
  },
  "Y6Zfg06vtE": {
    "pageNum": 285,
    "number": 5683,
    "text": {
      "tags": [
        "登山",
        "冥想",
        "宁静"
      ],
      "likes": 127,
      "bookmarks": 42
    }
  },
  "NnsMnQBfTu": {
    "pageNum": 285,
    "number": 5684,
    "text": {
      "tags": [
        "时光",
        "美丽",
        "人生"
      ],
      "likes": 127,
      "bookmarks": 37
    }
  },
  "3U2aC5_B4V": {
    "pageNum": 285,
    "number": 5685,
    "text": {
      "tags": [
        "哲理",
        "人生",
        "命运"
      ],
      "likes": 876,
      "bookmarks": 327
    }
  },
  "XQ2evPONaF": {
    "pageNum": 285,
    "number": 5686,
    "text": {
      "tags": [
        "离愁",
        "思乡",
        "人生"
      ],
      "likes": 127,
      "bookmarks": 37
    }
  },
  "gOmwSzLpxW": {
    "pageNum": 285,
    "number": 5687,
    "text": {
      "tags": [
        "神话",
        "古代文化",
        "仙女"
      ],
      "likes": 256,
      "bookmarks": 87
    }
  },
  "rAsQ7GmVPO": {
    "pageNum": 285,
    "number": 5688,
    "text": {
      "tags": [
        "文学",
        "诗歌",
        "传统文化"
      ],
      "likes": 127,
      "bookmarks": 42
    }
  },
  "pxQtTtrsBM": {
    "pageNum": 285,
    "number": 5689,
    "text": {
      "tags": [
        "诗歌",
        "爱情",
        "离别"
      ],
      "likes": 127,
      "bookmarks": 42
    }
  },
  "d8W0w7VwHc": {
    "pageNum": 285,
    "number": 5690,
    "text": {
      "tags": [
        "哲理",
        "人生",
        "修身养性"
      ],
      "likes": 127,
      "bookmarks": 37
    }
  },
  "rl8wEDhIgd": {
    "pageNum": 285,
    "number": 5691,
    "text": {
      "tags": [
        "家庭",
        "亲情",
        "传承"
      ],
      "likes": 87,
      "bookmarks": 32
    }
  },
  "aLR98neGZl": {
    "pageNum": 285,
    "number": 5692,
    "text": {
      "tags": [
        "寂静",
        "禅修",
        "冥想"
      ],
      "likes": 127,
      "bookmarks": 37
    }
  },
  "xstqxh3tqr": {
    "pageNum": 285,
    "number": 5693,
    "text": {
      "tags": [
        "冬天",
        "雪景",
        "季节"
      ],
      "likes": 87,
      "bookmarks": 32
    }
  },
  "Qz4xjgg27J": {
    "pageNum": 285,
    "number": 5694,
    "text": {
      "tags": [
        "诗歌",
        "写景",
        "屈原"
      ],
      "likes": 127,
      "bookmarks": 42
    }
  },
  "a02adOCme4": {
    "pageNum": 285,
    "number": 5695,
    "text": {
      "tags": [
        "古风",
        "文学",
        "怀旧"
      ],
      "likes": 2568,
      "bookmarks": 789
    }
  },
  "8xwgHgT6a1": {
    "pageNum": 285,
    "number": 5696,
    "text": {
      "tags": [
        "投资",
        "真诚",
        "情感"
      ],
      "likes": 127,
      "bookmarks": 37
    }
  },
  "6kuB_6LpmA": {
    "pageNum": 285,
    "number": 5697,
    "text": {
      "tags": [
        "自然",
        "田园",
        "诗歌"
      ],
      "likes": 127,
      "bookmarks": 42
    }
  },
  "_KaXWPwJll": {
    "pageNum": 285,
    "number": 5698,
    "text": {
      "tags": [
        "自然景观",
        "山峰"
      ],
      "likes": 127,
      "bookmarks": 42
    }
  },
  "nalvRJmDSK": {
    "pageNum": 285,
    "number": 5699,
    "text": {
      "tags": [
        "离别",
        "思念",
        "距离"
      ],
      "likes": 127,
      "bookmarks": 42
    }
  },
  "JeT8vqxnQH": {
    "pageNum": 285,
    "number": 5700,
    "text": {
      "tags": [
        "梦境",
        "乡愁",
        "故国",
        "自然"
      ],
      "likes": 127,
      "bookmarks": 42
    }
  },
  "Y_TzJsMLPP": {
    "pageNum": 286,
    "number": 5701,
    "text": {
      "tags": [
        "自然",
        "美景",
        "壮观"
      ],
      "likes": 127,
      "bookmarks": 42
    }
  },
  "XMof2So3lt": {
    "pageNum": 286,
    "number": 5702,
    "text": {
      "tags": [
        "学习",
        "人生",
        "成就"
      ],
      "likes": 127,
      "bookmarks": 42
    }
  },
  "RNq5I_AmBU": {
    "pageNum": 286,
    "number": 5703,
    "text": {
      "tags": [
        "官场",
        "政治",
        "权力"
      ],
      "likes": 127,
      "bookmarks": 42
    }
  },
  "E0GRG-kFw6": {
    "pageNum": 286,
    "number": 5704,
    "text": {
      "tags": [
        "养生",
        "健康",
        "饮食"
      ],
      "likes": 1278,
      "bookmarks": 456
    }
  },
  "-7ifJrwQEK": {
    "pageNum": 286,
    "number": 5705,
    "text": {
      "tags": [
        "人生",
        "自由",
        "追求"
      ],
      "likes": 127,
      "bookmarks": 37
    }
  },
  "qKgHmvQv-8": {
    "pageNum": 286,
    "number": 5706,
    "text": {
      "tags": [
        "相遇",
        "社交",
        "名利",
        "美丽"
      ],
      "likes": 876,
      "bookmarks": 427
    }
  },
  "iCX0VL_d2u": {
    "pageNum": 286,
    "number": 5707,
    "text": {
      "tags": [
        "期望",
        "希望",
        "农业",
        "自然"
      ],
      "likes": 127,
      "bookmarks": 42
    }
  },
  "KnlPF6OJUQ": {
    "pageNum": 286,
    "number": 5708,
    "text": {
      "tags": [
        "神话",
        "仙侠",
        "传说"
      ],
      "likes": 127,
      "bookmarks": 42
    }
  },
  "h5Uoc5kGmv": {
    "pageNum": 286,
    "number": 5709,
    "text": {
      "tags": [
        "忧愁",
        "悲伤",
        "痛苦"
      ],
      "likes": 127,
      "bookmarks": 42
    }
  },
  "sZHl3TCqFA": {
    "pageNum": 286,
    "number": 5710,
    "text": {
      "tags": [
        "古代文化",
        "历史"
      ],
      "likes": 127,
      "bookmarks": 42
    }
  },
  "MvM-ca1JBD": {
    "pageNum": 286,
    "number": 5711,
    "text": {
      "tags": [
        "自然",
        "风景",
        "壮美"
      ],
      "likes": 256,
      "bookmarks": 87
    }
  },
  "Ch9LZwCDE1": {
    "pageNum": 286,
    "number": 5712,
    "text": {
      "tags": [
        "时光",
        "流逝",
        "珍惜"
      ],
      "likes": 127,
      "bookmarks": 42
    }
  },
  "DmBVm4xrf1": {
    "pageNum": 286,
    "number": 5713,
    "text": {
      "tags": [
        "柳树",
        "自然",
        "怜悯"
      ],
      "likes": 127,
      "bookmarks": 37
    }
  },
  "oJxAA3g3mi": {
    "pageNum": 286,
    "number": 5714,
    "text": {
      "tags": [
        "古诗词",
        "旅行"
      ],
      "likes": 87,
      "bookmarks": 32
    }
  },
  "-fSQzcAdu6": {
    "pageNum": 286,
    "number": 5715,
    "text": {
      "tags": [
        "诗歌",
        "景色",
        "思乡"
      ],
      "likes": 256,
      "bookmarks": 87
    }
  },
  "qFVQBwCMrb": {
    "pageNum": 286,
    "number": 5716,
    "text": {
      "tags": [
        "文学",
        "爱情",
        "青春"
      ],
      "likes": 127,
      "bookmarks": 42
    }
  },
  "92aUmEG9NV": {
    "pageNum": 286,
    "number": 5717,
    "text": {
      "tags": [
        "秋天",
        "风景",
        "诗歌"
      ],
      "likes": 127,
      "bookmarks": 42
    }
  },
  "Xyg8VtmBqM": {
    "pageNum": 286,
    "number": 5718,
    "text": {
      "tags": [
        "自然",
        "月亮",
        "花朵",
        "风景"
      ],
      "likes": 127,
      "bookmarks": 42
    }
  },
  "PnjZtgIj30": {
    "pageNum": 286,
    "number": 5719,
    "text": {
      "tags": [
        "离别",
        "友情",
        "动物"
      ],
      "likes": 127,
      "bookmarks": 42
    }
  },
  "30_ucfQNUx": {
    "pageNum": 286,
    "number": 5720,
    "text": {
      "tags": [
        "音乐",
        "忧伤",
        "疾病"
      ],
      "likes": 127,
      "bookmarks": 42
    }
  },
  "ExR2diE6gm": {
    "pageNum": 287,
    "number": 5721,
    "text": {
      "tags": [
        "政治",
        "利益"
      ],
      "likes": 87,
      "bookmarks": 32
    }
  },
  "KYF_gN-nmV": {
    "pageNum": 287,
    "number": 5722,
    "text": {
      "tags": [
        "诗歌",
        "饮酒",
        "文学"
      ],
      "likes": 127,
      "bookmarks": 42
    }
  },
  "77qVMB3omz": {
    "pageNum": 287,
    "number": 5723,
    "text": {
      "tags": [
        "礼仪",
        "人际关系",
        "助人"
      ],
      "likes": 127,
      "bookmarks": 42
    }
  },
  "uVxzFzBd-K": {
    "pageNum": 287,
    "number": 5724,
    "text": {
      "tags": [
        "自信",
        "坚持",
        "成功"
      ],
      "likes": 127,
      "bookmarks": 42
    }
  },
  "efv6TuZq-r": {
    "pageNum": 287,
    "number": 5725,
    "text": {
      "tags": [
        "爱情",
        "人际关系",
        "态度"
      ],
      "likes": 127,
      "bookmarks": 42
    }
  },
  "Drjc0G6IFT": {
    "pageNum": 287,
    "number": 5726,
    "text": {
      "tags": [
        "爱情",
        "离别",
        "思念"
      ],
      "likes": 127,
      "bookmarks": 42
    }
  },
  "SHwqONnAjv": {
    "pageNum": 287,
    "number": 5727,
    "text": {
      "tags": [
        "人生",
        "哲理",
        "偶然"
      ],
      "likes": 127,
      "bookmarks": 42
    }
  },
  "d_aFeDgKBi": {
    "pageNum": 287,
    "number": 5728,
    "text": {
      "tags": [
        "领导力",
        "决策",
        "观察",
        "民意"
      ],
      "likes": 876,
      "bookmarks": 427
    }
  },
  "5tf9-E9nPF": {
    "pageNum": 287,
    "number": 5730,
    "text": {
      "tags": [
        "正义",
        "斩妖除魔",
        "侠义"
      ],
      "likes": 137,
      "bookmarks": 52
    }
  },
  "RmNWYmDXMK": {
    "pageNum": 287,
    "number": 5731,
    "text": {
      "tags": [
        "怀旧",
        "回忆",
        "情感"
      ],
      "likes": 256,
      "bookmarks": 87
    }
  },
  "zDD2je7NaL": {
    "pageNum": 287,
    "number": 5732,
    "text": {
      "tags": [
        "爱情",
        "离别",
        "相思"
      ],
      "likes": 127,
      "bookmarks": 42
    }
  },
  "wQmOr9S_Kr": {
    "pageNum": 287,
    "number": 5733,
    "text": {
      "tags": [
        "道德",
        "恶人",
        "警示"
      ],
      "likes": 127,
      "bookmarks": 42
    }
  },
  "Jjwyl951Dy": {
    "pageNum": 287,
    "number": 5734,
    "text": {
      "tags": [
        "文学",
        "写作",
        "创作",
        "表达"
      ],
      "likes": 1278,
      "bookmarks": 567
    }
  },
  "cUkjBOHxDr": {
    "pageNum": 287,
    "number": 5735,
    "text": {
      "tags": [
        "春天",
        "自然景观",
        "诗歌"
      ],
      "likes": 127,
      "bookmarks": 42
    }
  },
  "HBOH4i-iY9": {
    "pageNum": 287,
    "number": 5736,
    "text": {
      "tags": [
        "诗歌",
        "秋天",
        "自然"
      ],
      "likes": 87,
      "bookmarks": 32
    }
  },
  "MMs95d8zaB": {
    "pageNum": 287,
    "number": 5737,
    "text": {
      "tags": [
        "古代文化",
        "君臣关系",
        "国家"
      ],
      "likes": 1287,
      "bookmarks": 567
    }
  },
  "v9GBQVMRgj": {
    "pageNum": 287,
    "number": 5738,
    "text": {
      "tags": [
        "忠诚",
        "武士",
        "责任"
      ],
      "likes": 127,
      "bookmarks": 42
    }
  },
  "RWjQzv2SZG": {
    "pageNum": 287,
    "number": 5739,
    "text": {
      "tags": [
        "孤独",
        "忧伤",
        "失落"
      ],
      "likes": 127,
      "bookmarks": 42
    }
  },
  "p5B-Cz5Vt3": {
    "pageNum": 287,
    "number": 5740,
    "text": {
      "tags": [
        "离别",
        "思念",
        "友情"
      ],
      "likes": 127,
      "bookmarks": 42
    }
  },
  "B0cskGZe3w": {
    "pageNum": 288,
    "number": 5741,
    "text": {
      "tags": [
        "旅行",
        "探险",
        "自然"
      ],
      "likes": 127,
      "bookmarks": 42
    }
  },
  "CCInBNkrmz": {
    "pageNum": 288,
    "number": 5742,
    "text": {
      "tags": [
        "诗歌",
        "自然景观",
        "动物"
      ],
      "likes": 127,
      "bookmarks": 42
    }
  },
  "LWzzfE6Aco": {
    "pageNum": 288,
    "number": 5743,
    "text": {
      "tags": [
        "风景",
        "自然",
        "季节"
      ],
      "likes": 127,
      "bookmarks": 42
    }
  },
  "hVIvtYRjyy": {
    "pageNum": 288,
    "number": 5744,
    "text": {
      "tags": [
        "人生",
        "归乡",
        "追求"
      ],
      "likes": 127,
      "bookmarks": 37
    }
  },
  "smMJyiWnLF": {
    "pageNum": 288,
    "number": 5745,
    "text": {
      "tags": [
        "观察",
        "比喻",
        "竞争"
      ],
      "likes": 127,
      "bookmarks": 42
    }
  },
  "ozQc8tN56E": {
    "pageNum": 288,
    "number": 5746,
    "text": {
      "tags": [
        "诗歌",
        "文学",
        "哲理"
      ],
      "likes": 127,
      "bookmarks": 42
    }
  },
  "i3Y0_ZWryZ": {
    "pageNum": 288,
    "number": 5747,
    "text": {
      "tags": [
        "古风",
        "诗意",
        "山水"
      ],
      "likes": 127,
      "bookmarks": 42
    }
  },
  "92t7YLHLfr": {
    "pageNum": 288,
    "number": 5748,
    "text": {
      "tags": [
        "诗歌",
        "意境",
        "自然"
      ],
      "likes": 127,
      "bookmarks": 42
    }
  },
  "4h3hMr6Soo": {
    "pageNum": 288,
    "number": 5749,
    "text": {
      "tags": [
        "女性",
        "美丽",
        "自信",
        "幸福"
      ],
      "likes": 256,
      "bookmarks": 87
    }
  },
  "qYu3NQv-li": {
    "pageNum": 288,
    "number": 5750,
    "text": {
      "tags": [
        "古诗词",
        "文学",
        "唯美"
      ],
      "likes": 127,
      "bookmarks": 42
    }
  },
  "z73Go2n_fH": {
    "pageNum": 288,
    "number": 5751,
    "text": {
      "tags": [
        "寂静",
        "自然",
        "闲适"
      ],
      "likes": 87,
      "bookmarks": 32
    }
  },
  "kwMOEXHTqq": {
    "pageNum": 288,
    "number": 5752,
    "text": {
      "tags": [
        "迷茫",
        "未来",
        "希望"
      ],
      "likes": 127,
      "bookmarks": 42
    }
  },
  "iDPKpC1XKK": {
    "pageNum": 288,
    "number": 5753,
    "text": {
      "tags": [
        "哲学",
        "思考",
        "人生"
      ],
      "likes": 87,
      "bookmarks": 32
    }
  },
  "lkS7BQiz6i": {
    "pageNum": 288,
    "number": 5754,
    "text": {
      "tags": [
        "历史",
        "文化",
        "遗产"
      ],
      "likes": 127,
      "bookmarks": 43
    }
  },
  "w3YJm9gk-u": {
    "pageNum": 288,
    "number": 5755,
    "text": {
      "tags": [
        "爱情",
        "甜蜜",
        "微酸"
      ],
      "likes": 127,
      "bookmarks": 42
    }
  },
  "ePHyjUf-aX": {
    "pageNum": 288,
    "number": 5756,
    "text": {
      "tags": [
        "自然",
        "田园",
        "诗意"
      ],
      "likes": 127,
      "bookmarks": 42
    }
  },
  "w9F53AxfP6": {
    "pageNum": 288,
    "number": 5757,
    "text": {
      "tags": [
        "怀古",
        "人生",
        "思乡"
      ],
      "likes": 127,
      "bookmarks": 42
    }
  },
  "dknxRFNmm0": {
    "pageNum": 288,
    "number": 5758,
    "text": {
      "tags": [
        "养生",
        "生活态度"
      ],
      "likes": 87,
      "bookmarks": 32
    }
  },
  "5ho8pHxE0n": {
    "pageNum": 288,
    "number": 5759,
    "text": {
      "tags": [
        "季节",
        "离愁",
        "思乡",
        "寂寞"
      ],
      "likes": 127,
      "bookmarks": 42
    }
  },
  "b017Q0XjJj": {
    "pageNum": 288,
    "number": 5760,
    "text": {
      "tags": [
        "旅游",
        "人生",
        "感慨"
      ],
      "likes": 127,
      "bookmarks": 42
    }
  },
  "tVe9ABzeZA": {
    "pageNum": 289,
    "number": 5761,
    "text": {
      "tags": [
        "美食",
        "饮食"
      ],
      "likes": 127,
      "bookmarks": 42
    }
  },
  "VRMjhS4dQ9": {
    "pageNum": 289,
    "number": 5762,
    "text": {
      "tags": [
        "情感",
        "思乡",
        "怀旧"
      ],
      "likes": 256,
      "bookmarks": 87
    }
  },
  "i9ojmXJHBV": {
    "pageNum": 289,
    "number": 5763,
    "text": {
      "tags": [
        "垂钓",
        "春天",
        "自然景观",
        "杏花"
      ],
      "likes": 127,
      "bookmarks": 42
    }
  },
  "utUgosuWX-": {
    "pageNum": 289,
    "number": 5764,
    "text": {
      "tags": [
        "悲伤",
        "哀思",
        "情感"
      ],
      "likes": 127,
      "bookmarks": 37
    }
  },
  "s79jzCpz6j": {
    "pageNum": 289,
    "number": 5765,
    "text": {
      "tags": [
        "仁爱",
        "长寿"
      ],
      "likes": 127,
      "bookmarks": 37
    }
  },
  "-z3qK6CBq1": {
    "pageNum": 289,
    "number": 5766,
    "text": {
      "tags": [
        "古风",
        "文化",
        "艺术"
      ],
      "likes": 256,
      "bookmarks": 87
    }
  },
  "U_I7HN3AfE": {
    "pageNum": 289,
    "number": 5767,
    "text": {
      "tags": [
        "诗歌",
        "旅行",
        "人生"
      ],
      "likes": 127,
      "bookmarks": 42
    }
  },
  "o5hLBhuJsX": {
    "pageNum": 289,
    "number": 5768,
    "text": {
      "tags": [
        "季节",
        "动物",
        "自然"
      ],
      "likes": 87,
      "bookmarks": 32
    }
  },
  "vRRszahG-y": {
    "pageNum": 289,
    "number": 5769,
    "text": {
      "tags": [
        "自然",
        "田园",
        "诗歌"
      ],
      "likes": 127,
      "bookmarks": 42
    }
  },
  "7igX8KRQ-4": {
    "pageNum": 289,
    "number": 5770,
    "text": {
      "tags": [
        "古诗词",
        "文学"
      ],
      "likes": 87,
      "bookmarks": 32
    }
  },
  "E6-mKPh7Hc": {
    "pageNum": 289,
    "number": 5771,
    "text": {
      "tags": [
        "景色",
        "自然",
        "建筑"
      ],
      "likes": 127,
      "bookmarks": 42
    }
  },
  "hRhnX1V-72": {
    "pageNum": 289,
    "number": 5772,
    "text": {
      "tags": [
        "离别",
        "思念",
        "月夜"
      ],
      "likes": 127,
      "bookmarks": 42
    }
  },
  "Z1hCFbbtrq": {
    "pageNum": 289,
    "number": 5773,
    "text": {
      "tags": [
        "禅宗",
        "佛教",
        "冥想"
      ],
      "likes": 127,
      "bookmarks": 42
    }
  },
  "p8u5MMhF9m": {
    "pageNum": 289,
    "number": 5774,
    "text": {
      "tags": [
        "植物",
        "自然"
      ],
      "likes": 37,
      "bookmarks": 8
    }
  },
  "LPuBQLQOl1": {
    "pageNum": 289,
    "number": 5775,
    "text": {
      "tags": [
        "乡愁",
        "离别",
        "思乡",
        "诗歌"
      ],
      "likes": 256,
      "bookmarks": 87
    }
  },
  "qOdVwjc7A5": {
    "pageNum": 289,
    "number": 5776,
    "text": {
      "tags": [
        "奇幻",
        "冒险",
        "盗贼",
        "精灵"
      ],
      "likes": 127,
      "bookmarks": 42
    }
  },
  "PBgaSqNw_K": {
    "pageNum": 289,
    "number": 5777,
    "text": {
      "tags": [
        "生死",
        "情感"
      ],
      "likes": 127,
      "bookmarks": 42
    }
  },
  "faXUCy1Qpn": {
    "pageNum": 289,
    "number": 5778,
    "text": {
      "tags": [
        "哲理",
        "人生",
        "命运",
        "转变"
      ],
      "likes": 753,
      "bookmarks": 312
    }
  },
  "AefQIF_h-a": {
    "pageNum": 289,
    "number": 5779,
    "text": {
      "tags": [
        "离别",
        "友情",
        "饮酒"
      ],
      "likes": 127,
      "bookmarks": 42
    }
  },
  "Uyw_8NRiQf": {
    "pageNum": 289,
    "number": 5780,
    "text": {
      "tags": [
        "新年",
        "祝福",
        "时间"
      ],
      "likes": 1287,
      "bookmarks": 567
    }
  },
  "fqew65tVpr": {
    "pageNum": 290,
    "number": 5781,
    "text": {
      "tags": [
        "旅行",
        "远方",
        "寻找"
      ],
      "likes": 127,
      "bookmarks": 42
    }
  },
  "ErPd9XcKbf": {
    "pageNum": 290,
    "number": 5782,
    "text": {
      "tags": [
        "诗歌",
        "江河湖海",
        "自然"
      ],
      "likes": 127,
      "bookmarks": 42
    }
  },
  "y3XypBATbM": {
    "pageNum": 290,
    "number": 5783,
    "text": {
      "tags": [
        "梦境",
        "离愁",
        "寂静"
      ],
      "likes": 127,
      "bookmarks": 42
    }
  },
  "3xOmAE-Dmg": {
    "pageNum": 290,
    "number": 5784,
    "text": {
      "tags": [
        "旅行",
        "自然景观",
        "季节"
      ],
      "likes": 127,
      "bookmarks": 42
    }
  },
  "LoTjDo9xB8": {
    "pageNum": 290,
    "number": 5785,
    "text": {
      "tags": [
        "时光",
        "变化",
        "流逝"
      ],
      "likes": 127,
      "bookmarks": 37
    }
  },
  "ldGOr1Gzw0": {
    "pageNum": 290,
    "number": 5786,
    "text": {
      "tags": [
        "离别",
        "思念",
        "诗意"
      ],
      "likes": 127,
      "bookmarks": 37
    }
  },
  "Atwk7qRx8v": {
    "pageNum": 290,
    "number": 5787,
    "text": {
      "tags": [
        "历史",
        "政治",
        "国家"
      ],
      "likes": 127,
      "bookmarks": 42
    }
  },
  "gJa1q6BtCG": {
    "pageNum": 290,
    "number": 5788,
    "text": {
      "tags": [
        "人生",
        "哲理"
      ],
      "likes": 127,
      "bookmarks": 37
    }
  },
  "ytYBHqoagV": {
    "pageNum": 290,
    "number": 5789,
    "text": {
      "tags": [
        "诗歌",
        "爱情",
        "温馨"
      ],
      "likes": 127,
      "bookmarks": 42
    }
  },
  "5dBM08Z5Nk": {
    "pageNum": 290,
    "number": 5790,
    "text": {
      "tags": [
        "人生",
        "哲理",
        "励志"
      ],
      "likes": 127,
      "bookmarks": 42
    }
  },
  "XRKuRGyC76": {
    "pageNum": 290,
    "number": 5791,
    "text": {
      "tags": [
        "神话",
        "古代",
        "传说"
      ],
      "likes": 127,
      "bookmarks": 42
    }
  },
  "cLYt3uoFFx": {
    "pageNum": 290,
    "number": 5792,
    "text": {
      "tags": [
        "孤独",
        "情感",
        "内心世界"
      ],
      "likes": 127,
      "bookmarks": 42
    }
  },
  "GTxGRZhiTb": {
    "pageNum": 290,
    "number": 5793,
    "text": {
      "tags": [
        "春天",
        "自然景观",
        "梅花"
      ],
      "likes": 127,
      "bookmarks": 42
    }
  },
  "dqcbHsE8c2": {
    "pageNum": 290,
    "number": 5794,
    "text": {
      "tags": [
        "农业",
        "土地管理",
        "文化传统"
      ],
      "likes": 127,
      "bookmarks": 42
    }
  },
  "NawbWRpRdH": {
    "pageNum": 290,
    "number": 5795,
    "text": {
      "tags": [
        "灵活",
        "变通",
        "处事"
      ],
      "likes": 127,
      "bookmarks": 37
    }
  },
  "cjeRTYffGT": {
    "pageNum": 290,
    "number": 5796,
    "text": {
      "tags": [
        "历史",
        "文化",
        "古代兵器"
      ],
      "likes": 127,
      "bookmarks": 42
    }
  },
  "QCuy7aiKdL": {
    "pageNum": 290,
    "number": 5797,
    "text": {
      "tags": [
        "放松",
        "休息",
        "冥想"
      ],
      "likes": 87,
      "bookmarks": 23
    }
  },
  "pLf7Oidpad": {
    "pageNum": 290,
    "number": 5798,
    "text": {
      "tags": [
        "感官",
        "美好",
        "情感"
      ],
      "likes": 127,
      "bookmarks": 42
    }
  },
  "Cu9Mg1nlSq": {
    "pageNum": 290,
    "number": 5799,
    "text": {
      "tags": [
        "自然",
        "季节",
        "情感"
      ],
      "likes": 127,
      "bookmarks": 42
    }
  },
  "5m-9i8xAkd": {
    "pageNum": 290,
    "number": 5800,
    "text": {
      "tags": [
        "古风",
        "女性",
        "文学"
      ],
      "likes": 256,
      "bookmarks": 87
    }
  },
  "hvcg1zzOyr": {
    "pageNum": 291,
    "number": 5801,
    "text": {
      "tags": [
        "哲理",
        "人生",
        "思考"
      ],
      "likes": 127,
      "bookmarks": 42
    }
  },
  "ML3mcwqCuD": {
    "pageNum": 291,
    "number": 5802,
    "text": {
      "tags": [
        "神话",
        "传说",
        "龙"
      ],
      "likes": 127,
      "bookmarks": 42
    }
  },
  "qXjuMoSV21": {
    "pageNum": 291,
    "number": 5803,
    "text": {
      "tags": [
        "回忆",
        "相遇",
        "自然"
      ],
      "likes": 127,
      "bookmarks": 42
    }
  },
  "gd-Y2IbqVI": {
    "pageNum": 291,
    "number": 5804,
    "text": {
      "tags": [
        "孤独",
        "离别",
        "思念",
        "诗意"
      ],
      "likes": 127,
      "bookmarks": 42
    }
  },
  "2yx9_MfYkA": {
    "pageNum": 291,
    "number": 5805,
    "text": {
      "tags": [
        "自然景观",
        "山水风光"
      ],
      "likes": 87,
      "bookmarks": 42
    }
  },
  "ZKOMIBygVV": {
    "pageNum": 291,
    "number": 5806,
    "text": {
      "tags": [
        "历史",
        "战争",
        "忠诚"
      ],
      "likes": 127,
      "bookmarks": 42
    }
  },
  "579IyFz2rm": {
    "pageNum": 291,
    "number": 5807,
    "text": {
      "tags": [
        "手工艺",
        "纺织",
        "物价"
      ],
      "likes": 87,
      "bookmarks": 42
    }
  },
  "7V4e1JyBsM": {
    "pageNum": 291,
    "number": 5808,
    "text": {
      "tags": [
        "自然",
        "水",
        "荷花",
        "鱼"
      ],
      "likes": 127,
      "bookmarks": 42
    }
  },
  "mllxtNnSqC": {
    "pageNum": 291,
    "number": 5809,
    "text": {
      "tags": [
        "诗歌",
        "自然"
      ],
      "likes": 87,
      "bookmarks": 32
    }
  },
  "aQC3EGi1ed": {
    "pageNum": 291,
    "number": 5810,
    "text": {
      "tags": [
        "自然",
        "旅游",
        "孤独"
      ],
      "likes": 127,
      "bookmarks": 37
    }
  },
  "DgEG70hniG": {
    "pageNum": 291,
    "number": 5811,
    "text": {
      "tags": [
        "思乡",
        "眺望",
        "思念"
      ],
      "likes": 127,
      "bookmarks": 42
    }
  },
  "w19zBIb62A": {
    "pageNum": 291,
    "number": 5812,
    "text": {
      "tags": [
        "人生",
        "哲理",
        "励志"
      ],
      "likes": 127,
      "bookmarks": 42
    }
  },
  "gT9kKKf_Q6": {
    "pageNum": 291,
    "number": 5813,
    "text": {
      "tags": [
        "懒惰",
        "春天",
        "山水画"
      ],
      "likes": 127,
      "bookmarks": 42
    }
  },
  "EUxvx4IaWX": {
    "pageNum": 291,
    "number": 5815,
    "text": {
      "tags": [
        "哲理",
        "人生",
        "时间"
      ],
      "likes": 876,
      "bookmarks": 327
    }
  },
  "kVhPiqYmff": {
    "pageNum": 291,
    "number": 5816,
    "text": {
      "tags": [
        "离别",
        "悲伤",
        "忠诚"
      ],
      "likes": 127,
      "bookmarks": 42
    }
  },
  "pLwpsWD2jS": {
    "pageNum": 291,
    "number": 5817,
    "text": {
      "tags": [
        "爱情",
        "思念",
        "忧伤"
      ],
      "likes": 127,
      "bookmarks": 37
    }
  },
  "piTTF9tnRo": {
    "pageNum": 291,
    "number": 5818,
    "text": {
      "tags": [
        "诗歌",
        "景色",
        "自然"
      ],
      "likes": 87,
      "bookmarks": 32
    }
  },
  "oF_HJOW7eB": {
    "pageNum": 291,
    "number": 5819,
    "text": {
      "tags": [
        "亲情",
        "友情",
        "人生"
      ],
      "likes": 127,
      "bookmarks": 42
    }
  },
  "i5PTj-cI4f": {
    "pageNum": 291,
    "number": 5820,
    "text": {
      "tags": [
        "孤独",
        "抗拒改变",
        "传统"
      ],
      "likes": 127,
      "bookmarks": 37
    }
  },
  "C5zDbCtO5J": {
    "pageNum": 292,
    "number": 5821,
    "text": {
      "tags": [
        "修行",
        "道德"
      ],
      "likes": 127,
      "bookmarks": 42
    }
  },
  "jNVq0azeFb": {
    "pageNum": 292,
    "number": 5822,
    "text": {
      "tags": [
        "友情",
        "离别",
        "诗歌"
      ],
      "likes": 127,
      "bookmarks": 42
    }
  },
  "gNFl7TsTdB": {
    "pageNum": 292,
    "number": 5823,
    "text": {
      "tags": [
        "修养",
        "语言",
        "表达",
        "情感"
      ],
      "likes": 876,
      "bookmarks": 427
    }
  },
  "KYWxrllYCp": {
    "pageNum": 292,
    "number": 5824,
    "text": {
      "tags": [
        "武侠",
        "战斗",
        "动作"
      ],
      "likes": 876,
      "bookmarks": 427
    }
  },
  "iRbueIvl9l": {
    "pageNum": 292,
    "number": 5825,
    "text": {
      "tags": [
        "诗歌",
        "债务",
        "白菊",
        "失眠"
      ],
      "likes": 127,
      "bookmarks": 42
    }
  },
  "ig82cRlmKm": {
    "pageNum": 292,
    "number": 5826,
    "text": {
      "tags": [
        "战争",
        "政治",
        "历史"
      ],
      "likes": 127,
      "bookmarks": 42
    }
  },
  "5ZF93J3rkH": {
    "pageNum": 292,
    "number": 5827,
    "text": {
      "tags": [
        "离别",
        "思念",
        "相思"
      ],
      "likes": 127,
      "bookmarks": 37
    }
  },
  "oExX9WJ2dw": {
    "pageNum": 292,
    "number": 5828,
    "text": {
      "tags": [
        "自然",
        "风景",
        "诗歌"
      ],
      "likes": 127,
      "bookmarks": 37
    }
  },
  "4-a83sqJZH": {
    "pageNum": 292,
    "number": 5829,
    "text": {
      "tags": [
        "自然",
        "山水",
        "景色"
      ],
      "likes": 127,
      "bookmarks": 42
    }
  },
  "0InZhu5XVo": {
    "pageNum": 292,
    "number": 5830,
    "text": {
      "tags": [
        "古诗词",
        "景色",
        "地理"
      ],
      "likes": 127,
      "bookmarks": 42
    }
  },
  "U3lUkBwLSe": {
    "pageNum": 292,
    "number": 5831,
    "text": {
      "tags": [
        "学习",
        "人生",
        "历史"
      ],
      "likes": 127,
      "bookmarks": 42
    }
  },
  "m51TGSIkn1": {
    "pageNum": 292,
    "number": 5832,
    "text": {
      "tags": [
        "冷静",
        "个性",
        "审美"
      ],
      "likes": 127,
      "bookmarks": 42
    }
  },
  "FMyKuwWWVa": {
    "pageNum": 292,
    "number": 5833,
    "text": {
      "tags": [
        "花卉",
        "美学",
        "清新"
      ],
      "likes": 127,
      "bookmarks": 42
    }
  },
  "BwMWi0oyz9": {
    "pageNum": 292,
    "number": 5834,
    "text": {
      "tags": [
        "饮酒",
        "豁达",
        "心情"
      ],
      "likes": 127,
      "bookmarks": 42
    }
  },
  "N4_jexXj90": {
    "pageNum": 292,
    "number": 5835,
    "text": {
      "tags": [
        "伤感",
        "离别",
        "思念"
      ],
      "likes": 127,
      "bookmarks": 42
    }
  },
  "_3pI9NNeeU": {
    "pageNum": 292,
    "number": 5836,
    "text": {
      "tags": [
        "恐惧",
        "危险",
        "逃避"
      ],
      "likes": 127,
      "bookmarks": 42
    }
  },
  "PdB1WcOiKB": {
    "pageNum": 292,
    "number": 5837,
    "text": {
      "tags": [
        "离别",
        "难过",
        "告别"
      ],
      "likes": 127,
      "bookmarks": 37
    }
  },
  "eA3nSxv5QW": {
    "pageNum": 292,
    "number": 5838,
    "text": {
      "tags": [
        "忠诚",
        "恐惧",
        "修省"
      ],
      "likes": 127,
      "bookmarks": 37
    }
  },
  "74q3sbWQ8T": {
    "pageNum": 292,
    "number": 5839,
    "text": {
      "tags": [
        "历史",
        "政治",
        "文化"
      ],
      "likes": 127,
      "bookmarks": 42
    }
  },
  "7jllVaF1Gv": {
    "pageNum": 292,
    "number": 5840,
    "text": {
      "tags": [
        "诗歌",
        "约会",
        "夜晚"
      ],
      "likes": 127,
      "bookmarks": 42
    }
  },
  "ZHboOub2dp": {
    "pageNum": 293,
    "number": 5841,
    "text": {
      "tags": [
        "思念",
        "相思",
        "孤独",
        "寂寞"
      ],
      "likes": 127,
      "bookmarks": 42
    }
  },
  "lMM2MIYLZ7": {
    "pageNum": 293,
    "number": 5842,
    "text": {
      "tags": [
        "人生哲理",
        "自我认知"
      ],
      "likes": 1287,
      "bookmarks": 567
    }
  },
  "302z-7RZrh": {
    "pageNum": 293,
    "number": 5843,
    "text": {
      "tags": [
        "女性",
        "形容",
        "舞蹈"
      ],
      "likes": 127,
      "bookmarks": 42
    }
  },
  "sCvUB-5Jj1": {
    "pageNum": 293,
    "number": 5844,
    "text": {
      "tags": [
        "成长",
        "自我提升",
        "蜕变"
      ],
      "likes": 127,
      "bookmarks": 42
    }
  },
  "_5YaidBVB6": {
    "pageNum": 293,
    "number": 5845,
    "text": {
      "tags": [
        "历史",
        "文化"
      ],
      "likes": 127,
      "bookmarks": 37
    }
  },
  "2xek_QYg6W": {
    "pageNum": 293,
    "number": 5846,
    "text": {
      "tags": [
        "诗歌",
        "文学",
        "艺术"
      ],
      "likes": 127,
      "bookmarks": 42
    }
  },
  "PAcA-VwxeX": {
    "pageNum": 293,
    "number": 5847,
    "text": {
      "tags": [
        "爱情",
        "离别",
        "思念"
      ],
      "likes": 127,
      "bookmarks": 37
    }
  },
  "xNYXegYR1Q": {
    "pageNum": 293,
    "number": 5848,
    "text": {
      "tags": [
        "思念",
        "离别",
        "相思"
      ],
      "likes": 256,
      "bookmarks": 87
    }
  },
  "XEXpkW7yY5": {
    "pageNum": 293,
    "number": 5849,
    "text": {
      "tags": [
        "幽默",
        "误解"
      ],
      "likes": 127,
      "bookmarks": 42
    }
  },
  "0w0tU_XBr7": {
    "pageNum": 293,
    "number": 5850,
    "text": {
      "tags": [
        "怀旧",
        "回忆",
        "自然"
      ],
      "likes": 127,
      "bookmarks": 42
    }
  },
  "oME5R3m5dJ": {
    "pageNum": 293,
    "number": 5851,
    "text": {
      "tags": [
        "古风",
        "诗词",
        "居住"
      ],
      "likes": 127,
      "bookmarks": 42
    }
  },
  "biG35ag058": {
    "pageNum": 293,
    "number": 5852,
    "text": {
      "tags": [
        "季节",
        "离别",
        "思念",
        "自然"
      ],
      "likes": 127,
      "bookmarks": 42
    }
  },
  "f3ef87a37l": {
    "pageNum": 293,
    "number": 5853,
    "text": {
      "tags": [
        "阅读",
        "学习",
        "速度"
      ],
      "likes": 127,
      "bookmarks": 42
    }
  },
  "BGjNyCM1Hy": {
    "pageNum": 293,
    "number": 5854,
    "text": {
      "tags": [
        "友情",
        "人际关系",
        "困难"
      ],
      "likes": 127,
      "bookmarks": 42
    }
  },
  "2_OxRm2wWg": {
    "pageNum": 293,
    "number": 5855,
    "text": {
      "tags": [
        "自然",
        "山水",
        "田园",
        "诗意"
      ],
      "likes": 127,
      "bookmarks": 42
    }
  },
  "yljEg-juH1": {
    "pageNum": 293,
    "number": 5856,
    "text": {
      "tags": [
        "诗歌",
        "自然",
        "季节"
      ],
      "likes": 127,
      "bookmarks": 42
    }
  },
  "P9QYjA1EmI": {
    "pageNum": 293,
    "number": 5857,
    "text": {
      "tags": [
        "春天",
        "旅游",
        "离别"
      ],
      "likes": 127,
      "bookmarks": 42
    }
  },
  "3JmEMtlU88": {
    "pageNum": 293,
    "number": 5858,
    "text": {
      "tags": [
        "孤独",
        "思念",
        "落寞",
        "黄昏"
      ],
      "likes": 127,
      "bookmarks": 37
    }
  },
  "rte-F8ePSO": {
    "pageNum": 293,
    "number": 5859,
    "text": {
      "tags": [
        "诗歌",
        "豪放",
        "饮酒",
        "快乐"
      ],
      "likes": 789,
      "bookmarks": 321
    }
  },
  "aaa_pr1BVO": {
    "pageNum": 293,
    "number": 5860,
    "text": {
      "tags": [
        "历史",
        "战争",
        "英雄"
      ],
      "likes": 127,
      "bookmarks": 42
    }
  },
  "rrkN6p3fg1": {
    "pageNum": 294,
    "number": 5861,
    "text": {
      "tags": [
        "忠诚",
        "牺牲",
        "家庭"
      ],
      "likes": 127,
      "bookmarks": 42
    }
  },
  "dobrah2O3T": {
    "pageNum": 294,
    "number": 5862,
    "text": {
      "tags": [
        "诗歌",
        "送别",
        "美酒"
      ],
      "likes": 127,
      "bookmarks": 42
    }
  },
  "8McpQph08Q": {
    "pageNum": 294,
    "number": 5863,
    "text": {
      "tags": [
        "离别",
        "友情",
        "思念",
        "旅行"
      ],
      "likes": 127,
      "bookmarks": 42
    }
  },
  "DtRyUy0qAC": {
    "pageNum": 294,
    "number": 5864,
    "text": {
      "tags": [
        "自然",
        "美景",
        "诗意"
      ],
      "likes": 127,
      "bookmarks": 42
    }
  },
  "P-jW0y9pFP": {
    "pageNum": 294,
    "number": 5865,
    "text": {
      "tags": [
        "自然",
        "渔业",
        "诗歌"
      ],
      "likes": 127,
      "bookmarks": 42
    }
  },
  "YSKtLbmF5-": {
    "pageNum": 294,
    "number": 5866,
    "text": {
      "tags": [
        "政治",
        "行为",
        "士人"
      ],
      "likes": 127,
      "bookmarks": 42
    }
  },
  "oAoFg7wkex": {
    "pageNum": 294,
    "number": 5867,
    "text": {
      "tags": [
        "清廉",
        "贤人",
        "建筑"
      ],
      "likes": 127,
      "bookmarks": 37
    }
  },
  "3FkeUoHLBN": {
    "pageNum": 294,
    "number": 5868,
    "text": {
      "tags": [
        "安逸",
        "舒适",
        "居住"
      ],
      "likes": 127,
      "bookmarks": 42
    }
  },
  "4DXJK0rVBa": {
    "pageNum": 294,
    "number": 5869,
    "text": {
      "tags": [
        "人生",
        "时光",
        "老去"
      ],
      "likes": 127,
      "bookmarks": 42
    }
  },
  "ECPHL9opFV": {
    "pageNum": 294,
    "number": 5870,
    "text": {
      "tags": [
        "战争",
        "历史",
        "文化"
      ],
      "likes": 127,
      "bookmarks": 42
    }
  },
  "5m-rYx153y": {
    "pageNum": 294,
    "number": 5871,
    "text": {
      "tags": [
        "诗歌",
        "古风",
        "意境"
      ],
      "likes": 127,
      "bookmarks": 42
    }
  },
  "BM1J-wmSFS": {
    "pageNum": 294,
    "number": 5872,
    "text": {
      "tags": [
        "爱情",
        "离别",
        "相思"
      ],
      "likes": 2567,
      "bookmarks": 789
    }
  },
  "flyrPFTiNX": {
    "pageNum": 294,
    "number": 5873,
    "text": {
      "tags": [
        "自由",
        "生活",
        "艺术"
      ],
      "likes": 127,
      "bookmarks": 42
    }
  },
  "m48IvM3pyI": {
    "pageNum": 294,
    "number": 5874,
    "text": {
      "tags": [
        "动物",
        "旅行",
        "自然"
      ],
      "likes": 127,
      "bookmarks": 42
    }
  },
  "HPgUd2p3_A": {
    "pageNum": 294,
    "number": 5875,
    "text": {
      "tags": [
        "历史",
        "战争",
        "旅行"
      ],
      "likes": 127,
      "bookmarks": 42
    }
  },
  "6bGXqy_d9K": {
    "pageNum": 294,
    "number": 5877,
    "text": {
      "tags": [
        "佛教",
        "哲学",
        "人性"
      ],
      "likes": 1278,
      "bookmarks": 567
    }
  },
  "EX4-K0ku4n": {
    "pageNum": 294,
    "number": 5878,
    "text": {
      "tags": [
        "自然",
        "山水",
        "季节"
      ],
      "likes": 127,
      "bookmarks": 42
    }
  },
  "pGJSZyiSUF": {
    "pageNum": 294,
    "number": 5879,
    "text": {
      "tags": [
        "劳动",
        "生活",
        "职业"
      ],
      "likes": 87,
      "bookmarks": 32
    }
  },
  "79jK6vAuYI": {
    "pageNum": 294,
    "number": 5880,
    "text": {
      "tags": [
        "自然",
        "孤独",
        "景观"
      ],
      "likes": 127,
      "bookmarks": 37
    }
  },
  "7bxi4HOJ9d": {
    "pageNum": 295,
    "number": 5882,
    "text": {
      "tags": [
        "仙人",
        "爱情",
        "招手"
      ],
      "likes": 127,
      "bookmarks": 42
    }
  },
  "_ZtDlcPoSz": {
    "pageNum": 295,
    "number": 5883,
    "text": {
      "tags": [
        "教育",
        "家庭教育",
        "母爱"
      ],
      "likes": 1278,
      "bookmarks": 567
    }
  },
  "yokLXyItAX": {
    "pageNum": 295,
    "number": 5884,
    "text": {
      "tags": [
        "人生",
        "旅行",
        "回忆"
      ],
      "likes": 127,
      "bookmarks": 42
    }
  },
  "xEEcRvxhEF": {
    "pageNum": 295,
    "number": 5885,
    "text": {
      "tags": [
        "归乡",
        "离别",
        "期待"
      ],
      "likes": 127,
      "bookmarks": 37
    }
  },
  "Xt2qC9aRKJ": {
    "pageNum": 295,
    "number": 5886,
    "text": {
      "tags": [
        "力量",
        "决心",
        "毅力"
      ],
      "likes": 127,
      "bookmarks": 42
    }
  },
  "579zWDYAQr": {
    "pageNum": 295,
    "number": 5887,
    "text": {
      "tags": [
        "诗歌",
        "华丽",
        "古风"
      ],
      "likes": 127,
      "bookmarks": 42
    }
  },
  "vkbDC9i8M-": {
    "pageNum": 295,
    "number": 5888,
    "text": {
      "tags": [
        "夜晚",
        "动物",
        "自然"
      ],
      "likes": 127,
      "bookmarks": 42
    }
  },
  "JfSWc7w7Cg": {
    "pageNum": 295,
    "number": 5889,
    "text": {
      "tags": [
        "哲学",
        "人生",
        "心灵"
      ],
      "likes": 127,
      "bookmarks": 42
    }
  },
  "I4wZBNqNj1": {
    "pageNum": 295,
    "number": 5890,
    "text": {
      "tags": [
        "诗歌",
        "文学",
        "唐诗"
      ],
      "likes": 1287,
      "bookmarks": 567
    }
  },
  "ziB6YYm7XR": {
    "pageNum": 295,
    "number": 5891,
    "text": {
      "tags": [
        "孤独",
        "离别",
        "思念",
        "动物"
      ],
      "likes": 127,
      "bookmarks": 42
    }
  },
  "mVzUMtxJs4": {
    "pageNum": 295,
    "number": 5892,
    "text": {
      "tags": [
        "古风",
        "神话",
        "诗歌"
      ],
      "likes": 127,
      "bookmarks": 42
    }
  },
  "T6Xn7iZLvR": {
    "pageNum": 295,
    "number": 5894,
    "text": {
      "tags": [
        "山水",
        "诗歌",
        "文学"
      ],
      "likes": 87,
      "bookmarks": 32
    }
  },
  "LactwSvT42": {
    "pageNum": 295,
    "number": 5895,
    "text": {
      "tags": [
        "哲学",
        "运动",
        "自然"
      ],
      "likes": 127,
      "bookmarks": 42
    }
  },
  "LVKUDhxO7Y": {
    "pageNum": 295,
    "number": 5896,
    "text": {
      "tags": [
        "历史",
        "战争"
      ],
      "likes": 127,
      "bookmarks": 42
    }
  },
  "M87_rZrQ8x": {
    "pageNum": 295,
    "number": 5898,
    "text": {
      "tags": [
        "哲理",
        "人生",
        "修行"
      ],
      "likes": 127,
      "bookmarks": 56
    }
  },
  "WYYxwRmpEZ": {
    "pageNum": 295,
    "number": 5899,
    "text": {
      "tags": [
        "江南水乡",
        "旅行",
        "船只"
      ],
      "likes": 87,
      "bookmarks": 32
    }
  },
  "FzMA3ZYiXc": {
    "pageNum": 295,
    "number": 5900,
    "text": {
      "tags": [
        "战争",
        "历史",
        "边疆"
      ],
      "likes": 876,
      "bookmarks": 327
    }
  },
  "whwPTJkTV9": {
    "pageNum": 296,
    "number": 5901,
    "text": {
      "tags": [
        "娱乐",
        "游戏",
        "青春"
      ],
      "likes": 1287,
      "bookmarks": 456
    }
  },
  "yga4v7Mrhj": {
    "pageNum": 296,
    "number": 5902,
    "text": {
      "tags": [
        "礼仪",
        "尊重",
        "人际关系"
      ],
      "likes": 87,
      "bookmarks": 32
    }
  },
  "Gj1UoPpmJt": {
    "pageNum": 296,
    "number": 5903,
    "text": {
      "tags": [
        "旅行",
        "客人",
        "船"
      ],
      "likes": 127,
      "bookmarks": 42
    }
  },
  "sLH4IIIYMI": {
    "pageNum": 296,
    "number": 5904,
    "text": {
      "tags": [
        "诗歌",
        "自然景观",
        "花卉"
      ],
      "likes": 127,
      "bookmarks": 42
    }
  },
  "tSShZn7WMI": {
    "pageNum": 296,
    "number": 5905,
    "text": {
      "tags": [
        "诗歌",
        "景色",
        "历史"
      ],
      "likes": 127,
      "bookmarks": 42
    }
  },
  "fqDCpQRJ7c": {
    "pageNum": 296,
    "number": 5906,
    "text": {
      "tags": [
        "春天",
        "江河",
        "美食"
      ],
      "likes": 128,
      "bookmarks": 37
    }
  },
  "PHYQ4q_Y_b": {
    "pageNum": 296,
    "number": 5907,
    "text": {
      "tags": [
        "建筑",
        "水上",
        "荷花"
      ],
      "likes": 127,
      "bookmarks": 37
    }
  },
  "N7ucHLUsbf": {
    "pageNum": 296,
    "number": 5908,
    "text": {
      "tags": [
        "豁达",
        "生活态度",
        "乐观"
      ],
      "likes": 127,
      "bookmarks": 37
    }
  },
  "he2z2oktGD": {
    "pageNum": 296,
    "number": 5909,
    "text": {
      "tags": [
        "忠诚",
        "家庭",
        "亲情",
        "义气"
      ],
      "likes": 127,
      "bookmarks": 42
    }
  },
  "BPAksh6EzC": {
    "pageNum": 296,
    "number": 5910,
    "text": {
      "tags": [
        "文学",
        "历史"
      ],
      "likes": 127,
      "bookmarks": 42
    }
  },
  "jg-qDhfN_Y": {
    "pageNum": 296,
    "number": 5911,
    "text": {
      "tags": [
        "家庭",
        "团聚",
        "离别"
      ],
      "likes": 256,
      "bookmarks": 87
    }
  },
  "tqiAXdS91O": {
    "pageNum": 296,
    "number": 5912,
    "text": {
      "tags": [
        "古风",
        "诗词",
        "女性"
      ],
      "likes": 127,
      "bookmarks": 42
    }
  },
  "Fg2R-CC0py": {
    "pageNum": 296,
    "number": 5913,
    "text": {
      "tags": [
        "动物",
        "人性",
        "文化"
      ],
      "likes": 127,
      "bookmarks": 42
    }
  },
  "dNn5vEdBeb": {
    "pageNum": 296,
    "number": 5914,
    "text": {
      "tags": [
        "神话",
        "传说",
        "仙侠"
      ],
      "likes": 127,
      "bookmarks": 42
    }
  },
  "Fd8HGjiUVl": {
    "pageNum": 296,
    "number": 5915,
    "text": {
      "tags": [
        "音乐",
        "器乐",
        "战争"
      ],
      "likes": 127,
      "bookmarks": 42
    }
  },
  "qhxfj1mmm5": {
    "pageNum": 296,
    "number": 5916,
    "text": {
      "tags": [
        "爱情",
        "离别",
        "思念"
      ],
      "likes": 127,
      "bookmarks": 42
    }
  },
  "YqbJElqtFN": {
    "pageNum": 296,
    "number": 5917,
    "text": {
      "tags": [
        "音乐",
        "古代文化"
      ],
      "likes": 1287,
      "bookmarks": 567
    }
  },
  "VFsM8kIf2f": {
    "pageNum": 296,
    "number": 5918,
    "text": {
      "tags": [
        "悲伤",
        "失落",
        "离别",
        "思念"
      ],
      "likes": 127,
      "bookmarks": 37
    }
  },
  "3N_X3lZrKI": {
    "pageNum": 296,
    "number": 5919,
    "text": {
      "tags": [
        "权力",
        "正义",
        "信仰"
      ],
      "likes": 127,
      "bookmarks": 42
    }
  },
  "xXzMQCc5qD": {
    "pageNum": 296,
    "number": 5920,
    "text": {
      "tags": [
        "诗歌",
        "月亮",
        "夜晚",
        "怀旧"
      ],
      "likes": 127,
      "bookmarks": 42
    }
  },
  "9TBrzaLvLL": {
    "pageNum": 297,
    "number": 5921,
    "text": {
      "tags": [
        "死亡",
        "绝望",
        "悲伤"
      ],
      "likes": 127,
      "bookmarks": 42
    }
  },
  "b9AWAeIiv5": {
    "pageNum": 297,
    "number": 5922,
    "text": {
      "tags": [
        "人生",
        "时光",
        "成长"
      ],
      "likes": 876,
      "bookmarks": 327
    }
  },
  "nhcuYSEt1Q": {
    "pageNum": 297,
    "number": 5923,
    "text": {
      "tags": [
        "季节",
        "萧瑟",
        "荒凉"
      ],
      "likes": 127,
      "bookmarks": 42
    }
  },
  "2JwL3sppGe": {
    "pageNum": 297,
    "number": 5924,
    "text": {
      "tags": [
        "口才",
        "写作",
        "表达能力"
      ],
      "likes": 8765,
      "bookmarks": 4321
    }
  },
  "SrxP7B2qFI": {
    "pageNum": 297,
    "number": 5925,
    "text": {
      "tags": [
        "诗歌",
        "唐诗",
        "爱情"
      ],
      "likes": 127,
      "bookmarks": 42
    }
  },
  "t5rzYg31Iw": {
    "pageNum": 297,
    "number": 5926,
    "text": {
      "tags": [
        "赌博",
        "胜利",
        "历史"
      ],
      "likes": 127,
      "bookmarks": 42
    }
  },
  "2WhYk_F0FC": {
    "pageNum": 297,
    "number": 5927,
    "text": {
      "tags": [
        "领导力",
        "管理",
        "成功"
      ],
      "likes": 1287,
      "bookmarks": 567
    }
  },
  "0Jjz0o6y5N": {
    "pageNum": 297,
    "number": 5928,
    "text": {
      "tags": [
        "自由",
        "无拘束",
        "生态"
      ],
      "likes": 127,
      "bookmarks": 42
    }
  },
  "dntlAZvZLT": {
    "pageNum": 297,
    "number": 5929,
    "text": {
      "tags": [
        "诗歌",
        "饮酒",
        "快乐"
      ],
      "likes": 127,
      "bookmarks": 42
    }
  },
  "x4OxvcLHW1": {
    "pageNum": 297,
    "number": 5930,
    "text": {
      "tags": [
        "稳定",
        "持久",
        "耐久"
      ],
      "likes": 127,
      "bookmarks": 57
    }
  },
  "N3AfHSnO7h": {
    "pageNum": 297,
    "number": 5931,
    "text": {
      "tags": [
        "宫廷",
        "孤独",
        "冷静"
      ],
      "likes": 127,
      "bookmarks": 43
    }
  },
  "GvdRxOG9Il": {
    "pageNum": 297,
    "number": 5932,
    "text": {
      "tags": [
        "古风",
        "文化",
        "美容"
      ],
      "likes": 256,
      "bookmarks": 87
    }
  },
  "yPW7_8t8av": {
    "pageNum": 297,
    "number": 5933,
    "text": {
      "tags": [
        "旅行",
        "思乡",
        "回忆"
      ],
      "likes": 127,
      "bookmarks": 42
    }
  },
  "4hdrCvMdFD": {
    "pageNum": 297,
    "number": 5934,
    "text": {
      "tags": [
        "伤感",
        "音乐",
        "情感"
      ],
      "likes": 1278,
      "bookmarks": 456
    }
  },
  "F8XWAqB_Dt": {
    "pageNum": 297,
    "number": 5935,
    "text": {
      "tags": [
        "哲理",
        "人生",
        "自然"
      ],
      "likes": 127,
      "bookmarks": 42
    }
  },
  "OmUJTnJmHq": {
    "pageNum": 297,
    "number": 5936,
    "text": {
      "tags": [
        "诗歌",
        "古风"
      ],
      "likes": 87,
      "bookmarks": 42
    }
  },
  "BDdLz0lAMP": {
    "pageNum": 297,
    "number": 5937,
    "text": {
      "tags": [
        "信仰",
        "神话",
        "宗教"
      ],
      "likes": 127,
      "bookmarks": 42
    }
  },
  "P5qWi5X12a": {
    "pageNum": 297,
    "number": 5938,
    "text": {
      "tags": [
        "采摘",
        "自然",
        "柔和"
      ],
      "likes": 127,
      "bookmarks": 42
    }
  },
  "G71itDDUGO": {
    "pageNum": 297,
    "number": 5939,
    "text": {
      "tags": [
        "古风",
        "怀旧",
        "季节"
      ],
      "likes": 87,
      "bookmarks": 23
    }
  },
  "MkcTVZqO5i": {
    "pageNum": 297,
    "number": 5940,
    "text": {
      "tags": [
        "诗歌",
        "爱情",
        "离别"
      ],
      "likes": 789,
      "bookmarks": 321
    }
  },
  "8xljohoPhO": {
    "pageNum": 298,
    "number": 5941,
    "text": {
      "tags": [
        "美貌",
        "宫廷",
        "爱情"
      ],
      "likes": 8765,
      "bookmarks": 4321
    }
  },
  "IpqL3NxnEi": {
    "pageNum": 298,
    "number": 5942,
    "text": {
      "tags": [
        "社会",
        "政治",
        "历史"
      ],
      "likes": 127,
      "bookmarks": 42
    }
  },
  "d9nqLrtA_8": {
    "pageNum": 298,
    "number": 5943,
    "text": {
      "tags": [
        "旅行",
        "历史",
        "文化"
      ],
      "likes": 1278,
      "bookmarks": 567
    }
  },
  "M7dDPX6R3I": {
    "pageNum": 298,
    "number": 5944,
    "text": {
      "tags": [
        "闲适",
        "自然",
        "生活"
      ],
      "likes": 127,
      "bookmarks": 42
    }
  },
  "1djZJUFj-t": {
    "pageNum": 298,
    "number": 5945,
    "text": {
      "tags": [
        "植物",
        "自然",
        "生命"
      ],
      "likes": 127,
      "bookmarks": 37
    }
  },
  "2wqMpkehWy": {
    "pageNum": 298,
    "number": 5947,
    "text": {
      "tags": [
        "离别",
        "思念",
        "爱情"
      ],
      "likes": 127,
      "bookmarks": 42
    }
  },
  "Rw_Aasz4F1": {
    "pageNum": 298,
    "number": 5948,
    "text": {
      "tags": [
        "武侠",
        "战斗",
        "武器"
      ],
      "likes": 127,
      "bookmarks": 42
    }
  },
  "WAezVGYphy": {
    "pageNum": 298,
    "number": 5949,
    "text": {
      "tags": [
        "离别",
        "思念",
        "悲伤",
        "诗歌"
      ],
      "likes": 127,
      "bookmarks": 37
    }
  },
  "-z7t7OwnRd": {
    "pageNum": 298,
    "number": 5950,
    "text": {
      "tags": [
        "人生",
        "情感",
        "团圆"
      ],
      "likes": 876,
      "bookmarks": 327
    }
  },
  "pATwBovWuw": {
    "pageNum": 298,
    "number": 5951,
    "text": {
      "tags": [
        "佛教",
        "修行",
        "心灵",
        "苦空"
      ],
      "likes": 127,
      "bookmarks": 37
    }
  },
  "LSAtjQDpD-": {
    "pageNum": 298,
    "number": 5952,
    "text": {
      "tags": [
        "古风",
        "旅行",
        "历史"
      ],
      "likes": 127,
      "bookmarks": 42
    }
  },
  "du_FxwFJdk": {
    "pageNum": 298,
    "number": 5953,
    "text": {
      "tags": [
        "离别",
        "家庭矛盾",
        "人生抉择"
      ],
      "likes": 127,
      "bookmarks": 43
    }
  },
  "NpLbGAMxMk": {
    "pageNum": 298,
    "number": 5954,
    "text": {
      "tags": [
        "自然景观",
        "江河湖海",
        "日出日落",
        "云彩"
      ],
      "likes": 1287,
      "bookmarks": 567
    }
  },
  "XMjgk0GjhY": {
    "pageNum": 298,
    "number": 5955,
    "text": {
      "tags": [
        "友情",
        "人生",
        "思考"
      ],
      "likes": 127,
      "bookmarks": 37
    }
  },
  "bVLNvQdbqO": {
    "pageNum": 298,
    "number": 5956,
    "text": {
      "tags": [
        "奋斗",
        "努力",
        "坚持"
      ],
      "likes": 127,
      "bookmarks": 42
    }
  },
  "Zt5EKUHPHA": {
    "pageNum": 298,
    "number": 5957,
    "text": {
      "tags": [
        "古诗词",
        "文学"
      ],
      "likes": 87,
      "bookmarks": 32
    }
  },
  "WeaYfFt5nx": {
    "pageNum": 298,
    "number": 5958,
    "text": {
      "tags": [
        "励志",
        "奋斗",
        "成功"
      ],
      "likes": 876,
      "bookmarks": 324
    }
  },
  "dxw8qiuVRd": {
    "pageNum": 298,
    "number": 5959,
    "text": {
      "tags": [
        "距离",
        "思念",
        "乡愁"
      ],
      "likes": 127,
      "bookmarks": 37
    }
  },
  "_BsI3BHfHe": {
    "pageNum": 298,
    "number": 5960,
    "text": {
      "tags": [
        "人生",
        "奋斗",
        "励志"
      ],
      "likes": 127,
      "bookmarks": 42
    }
  },
  "V3HZq4kdiN": {
    "pageNum": 299,
    "number": 5961,
    "text": {
      "tags": [
        "离别",
        "忧愁",
        "无奈"
      ],
      "likes": 87,
      "bookmarks": 32
    }
  },
  "vSZhZe0s3K": {
    "pageNum": 299,
    "number": 5962,
    "text": {
      "tags": [
        "怀旧",
        "景色",
        "自然"
      ],
      "likes": 256,
      "bookmarks": 87
    }
  },
  "uOcGSYkbgl": {
    "pageNum": 299,
    "number": 5963,
    "text": {
      "tags": [
        "悲伤",
        "无助",
        "饥饿"
      ],
      "likes": 37,
      "bookmarks": 8
    }
  },
  "sCD5NYDQ09": {
    "pageNum": 299,
    "number": 5964,
    "text": {
      "tags": [
        "古风",
        "诗词",
        "女性"
      ],
      "likes": 127,
      "bookmarks": 42
    }
  },
  "LJz6kuOsKi": {
    "pageNum": 299,
    "number": 5965,
    "text": {
      "tags": [
        "旅行",
        "使命",
        "传达信息"
      ],
      "likes": 127,
      "bookmarks": 42
    }
  },
  "HilnPFN83O": {
    "pageNum": 299,
    "number": 5966,
    "text": {
      "tags": [
        "感慨",
        "人生",
        "哲理"
      ],
      "likes": 1278,
      "bookmarks": 567
    }
  },
  "YcC-S6Fhny": {
    "pageNum": 299,
    "number": 5967,
    "text": {
      "tags": [
        "爱情",
        "婚姻",
        "人生"
      ],
      "likes": 1278,
      "bookmarks": 456
    }
  },
  "DARYZduDYx": {
    "pageNum": 299,
    "number": 5968,
    "text": {
      "tags": [
        "历史",
        "功绩"
      ],
      "likes": 87,
      "bookmarks": 32
    }
  },
  "SyI4vSRhUF": {
    "pageNum": 299,
    "number": 5969,
    "text": {
      "tags": [
        "人生",
        "历程",
        "奋斗"
      ],
      "likes": 127,
      "bookmarks": 42
    }
  },
  "5OsI28OOEB": {
    "pageNum": 299,
    "number": 5970,
    "text": {
      "tags": [
        "自然",
        "诗歌",
        "哲学"
      ],
      "likes": 127,
      "bookmarks": 37
    }
  },
  "fnWNUde05z": {
    "pageNum": 299,
    "number": 5971,
    "text": {
      "tags": [
        "自然",
        "旅行",
        "诗歌"
      ],
      "likes": 127,
      "bookmarks": 42
    }
  },
  "O3A7oUbx9R": {
    "pageNum": 299,
    "number": 5972,
    "text": {
      "tags": [
        "历史",
        "文化",
        "赞美"
      ],
      "likes": 1287,
      "bookmarks": 567
    }
  },
  "oBdnoTLbbw": {
    "pageNum": 299,
    "number": 5973,
    "text": {
      "tags": [
        "历史",
        "文化",
        "旅行"
      ],
      "likes": 127,
      "bookmarks": 42
    }
  },
  "7wGW-v8ORK": {
    "pageNum": 299,
    "number": 5974,
    "text": {
      "tags": [
        "利他主义",
        "道德",
        "人生哲理"
      ],
      "likes": 127,
      "bookmarks": 37
    }
  },
  "XGcwZe7mlQ": {
    "pageNum": 299,
    "number": 5975,
    "text": {
      "tags": [
        "古风",
        "唯美",
        "意境"
      ],
      "likes": 876,
      "bookmarks": 327
    }
  },
  "Obt0vDYwAs": {
    "pageNum": 299,
    "number": 5976,
    "text": {
      "tags": [
        "自然",
        "风景",
        "水"
      ],
      "likes": 87,
      "bookmarks": 32
    }
  },
  "dK1Ps1mZuO": {
    "pageNum": 299,
    "number": 5977,
    "text": {
      "tags": [
        "奇幻",
        "神话",
        "探险"
      ],
      "likes": 127,
      "bookmarks": 42
    }
  },
  "99rAQJiRqD": {
    "pageNum": 299,
    "number": 5978,
    "text": {
      "tags": [
        "冬天",
        "自然景观",
        "诗歌"
      ],
      "likes": 87,
      "bookmarks": 32
    }
  },
  "X-x3jUqwgo": {
    "pageNum": 299,
    "number": 5979,
    "text": {
      "tags": [
        "悲伤",
        "孤独",
        "失落"
      ],
      "likes": 127,
      "bookmarks": 42
    }
  },
  "2KzLJiZqRF": {
    "pageNum": 299,
    "number": 5980,
    "text": {
      "tags": [
        "旅行",
        "交通",
        "生活"
      ],
      "likes": 127,
      "bookmarks": 42
    }
  },
  "6cxURPxsLU": {
    "pageNum": 300,
    "number": 5981,
    "text": {
      "tags": [
        "人生",
        "快乐",
        "幸福",
        "命运"
      ],
      "likes": 1287,
      "bookmarks": 567
    }
  },
  "2gy9wE31CB": {
    "pageNum": 300,
    "number": 5983,
    "text": {
      "tags": [
        "离别",
        "送别",
        "诗歌"
      ],
      "likes": 127,
      "bookmarks": 42
    }
  },
  "6Z5edaJBPg": {
    "pageNum": 300,
    "number": 5984,
    "text": {
      "tags": [
        "爱情",
        "悲伤",
        "失望"
      ],
      "likes": 127,
      "bookmarks": 42
    }
  },
  "8If-1TCupB": {
    "pageNum": 300,
    "number": 5985,
    "text": {
      "tags": [
        "清晨",
        "日出",
        "家庭",
        "生活"
      ],
      "likes": 128,
      "bookmarks": 37
    }
  },
  "NsyxCWumGw": {
    "pageNum": 300,
    "number": 5986,
    "text": {
      "tags": [
        "历史",
        "文化"
      ],
      "likes": 127,
      "bookmarks": 42
    }
  },
  "gekXKC58Ou": {
    "pageNum": 300,
    "number": 5987,
    "text": {
      "tags": [
        "古风",
        "诗词",
        "意境"
      ],
      "likes": 127,
      "bookmarks": 42
    }
  },
  "o06VVbVg5Y": {
    "pageNum": 300,
    "number": 5988,
    "text": {
      "tags": [
        "爱情",
        "春天",
        "美景"
      ],
      "likes": 127,
      "bookmarks": 42
    }
  },
  "d4xCEtpSq0": {
    "pageNum": 300,
    "number": 5989,
    "text": {
      "tags": [
        "自然景观",
        "旅游",
        "文化遗产"
      ],
      "likes": 127,
      "bookmarks": 42
    }
  },
  "k04wfofTOU": {
    "pageNum": 300,
    "number": 5990,
    "text": {
      "tags": [
        "仁爱",
        "长寿"
      ],
      "likes": 127,
      "bookmarks": 37
    }
  },
  "DKRE-MDsev": {
    "pageNum": 300,
    "number": 5991,
    "text": {
      "tags": [
        "自然",
        "景色",
        "美感",
        "艺术"
      ],
      "likes": 127,
      "bookmarks": 42
    }
  },
  "G7dhyhF0UJ": {
    "pageNum": 300,
    "number": 5992,
    "text": {
      "tags": [
        "哲学",
        "人生",
        "行为"
      ],
      "likes": 127,
      "bookmarks": 42
    }
  },
  "IhSTtnceZt": {
    "pageNum": 300,
    "number": 5993,
    "text": {
      "tags": [
        "爱情",
        "离别",
        "悲伤"
      ],
      "likes": 127,
      "bookmarks": 42
    }
  },
  "cZFm8MF515": {
    "pageNum": 300,
    "number": 5994,
    "text": {
      "tags": [
        "山水",
        "景观",
        "音乐"
      ],
      "likes": 127,
      "bookmarks": 42
    }
  },
  "gVieEoVCqJ": {
    "pageNum": 300,
    "number": 5995,
    "text": {
      "tags": [
        "友情",
        "珍惜",
        "人生"
      ],
      "likes": 127,
      "bookmarks": 37
    }
  },
  "Qkk18ARwHy": {
    "pageNum": 300,
    "number": 5996,
    "text": {
      "tags": [
        "船夫",
        "湖泊",
        "自然"
      ],
      "likes": 127,
      "bookmarks": 42
    }
  },
  "CCNfcPDvK_": {
    "pageNum": 300,
    "number": 5997,
    "text": {
      "tags": [
        "孤独",
        "雨夜",
        "自然"
      ],
      "likes": 127,
      "bookmarks": 42
    }
  },
  "OcolmYsVlo": {
    "pageNum": 300,
    "number": 5998,
    "text": {
      "tags": [
        "思考",
        "关爱",
        "人际关系"
      ],
      "likes": 1278,
      "bookmarks": 567
    }
  },
  "24ulnifKrg": {
    "pageNum": 300,
    "number": 5999,
    "text": {
      "tags": [
        "女性",
        "文学",
        "古代"
      ],
      "likes": 127,
      "bookmarks": 42
    }
  },
  "b7nLxdbS8T": {
    "pageNum": 300,
    "number": 6000,
    "text": {
      "tags": [
        "生活",
        "情感",
        "回忆",
        "人生"
      ],
      "likes": 127,
      "bookmarks": 42
    }
  },
  "tVhqHl6m2a": {
    "pageNum": 301,
    "number": 6002,
    "text": {
      "tags": [
        "旅游",
        "自然景观",
        "宁静",
        "美好"
      ],
      "likes": 127,
      "bookmarks": 42
    }
  },
  "tgDZtxkTo7": {
    "pageNum": 301,
    "number": 6003,
    "text": {
      "tags": [
        "哲学",
        "圣人"
      ],
      "likes": 87,
      "bookmarks": 42
    }
  },
  "86Vz-0AUdk": {
    "pageNum": 301,
    "number": 6004,
    "text": {
      "tags": [
        "爱情",
        "诗歌"
      ],
      "likes": 127,
      "bookmarks": 42
    }
  },
  "e3CoaJ1vvJ": {
    "pageNum": 301,
    "number": 6005,
    "text": {
      "tags": [
        "自然",
        "风景",
        "气息"
      ],
      "likes": 127,
      "bookmarks": 42
    }
  },
  "giWnsTCj29": {
    "pageNum": 301,
    "number": 6006,
    "text": {
      "tags": [
        "忠诚",
        "爱国"
      ],
      "likes": 127,
      "bookmarks": 37
    }
  },
  "_IxxI8OG2Z": {
    "pageNum": 301,
    "number": 6007,
    "text": {
      "tags": [
        "娱乐",
        "休闲"
      ],
      "likes": 87,
      "bookmarks": 32
    }
  },
  "sOwJFH3VUL": {
    "pageNum": 301,
    "number": 6008,
    "text": {
      "tags": [
        "爱情",
        "感情"
      ],
      "likes": 127,
      "bookmarks": 42
    }
  }
}